xchatbot.py
xchatbot-0.5.0.dist-info/licenses/LICENSE
xchatbot-0.5.0.dist-info/METADATA
xchatbot-0.5.0.dist-info/WHEEL
xchatbot-0.5.0.dist-info/top_level.txt
xchatbot-0.5.0.dist-info/RECORD
