Metadata-Version: 2.4
Name: xchatbot
Version: 0.5.0
Summary: the Xtensible XMPP Chat Bot
Author-email: Fabio Comuni <fabrixxm@gmail.com>
License-Expression: GPL-3.0-or-later
Project-URL: Homepage, https://git.sr.ht/~fabrixxm/xchatbot
Project-URL: Documentation, https://xchatbot.readthedocs.io/
Classifier: Development Status :: 4 - Beta
Classifier: Intended Audience :: Developers
Classifier: Operating System :: MacOS :: MacOS X
Classifier: Operating System :: Microsoft :: Windows
Classifier: Operating System :: POSIX
Classifier: Programming Language :: Python :: 3
Classifier: Topic :: Communications :: Chat
License-File: LICENSE
Requires-Dist: nbxmpp<7.0.0,>=4.0.0
Requires-Dist: PyGObject<3.60.0,>=3.40.0
Provides-Extra: dev
Requires-Dist: build; extra == "dev"
Requires-Dist: setuptools; extra == "dev"
Requires-Dist: wheel; extra == "dev"
Dynamic: license-file
